{
  "gitSyncId": "671b096154c46730aaa1eabc_655df551-fc5c-4ce3-8e3b-8a8797df72b8",
  "id": "应用详情_utils.getLastDays",
  "pluginId": "js-plugin",
  "pluginType": "JS",
  "unpublishedAction": {
    "actionConfiguration": {
      "encodeParamsToggle": true,
      "jsArguments": [
        {
          "name": "dayNum"
        }
      ],
      "paginationType": "NONE",
      "timeoutInMillisecond": 10000
    },
    "collectionId": "应用详情_utils",
    "confirmBeforeExecute": false,
    "datasource": {
      "isAutoGenerated": false,
      "name": "UNUSED_DATASOURCE",
      "pluginId": "js-plugin"
    },
    "dynamicBindingPathList": [
      {
        "key": "body"
      }
    ],
    "executeOnLoad": false,
    "fullyQualifiedName": "utils.getLastDays",
    "name": "getLastDays",
    "pageId": "应用详情",
    "userSetOnLoad": false
  }
}