{
  "gitSyncId": "671b096154c46730aaa1eabc_6c6ddb77-02fe-4157-a83e-00bdc3198b64",
  "id": "应用报表_AppsQueryByPage",
  "pluginId": "postgres-plugin",
  "pluginType": "DB",
  "unpublishedAction": {
    "actionConfiguration": {
      "body": "SELECT\n    m.app_id, \n    t.name as WorkspaceName,\n    a.name as APPName,\n    (sum(m.message_tokens) + sum(m.answer_tokens)) as token_count,\n    sum(m.total_price) as total_price,\n\t\tcount(*) as message_count,\n\t\tcount(distinct m.from_end_user_id) as terminal_count\nFROM \n    messages m\t\nJOIN \n    apps a\nON \n    m.app_id = a.id\nJOIN \n    tenants t \nON \n    a.tenant_id = t.id \nWHERE\n  a.name ilike '%{{Table1.searchText}}%'\t\t\t\nGROUP BY \n    t.name,m.app_id, a.name \nORDER BY     \n    \"{{Table1.sortOrder.column || 'token_count'}}\" {{Table1.sortOrder.order !== \"desc\" ? \"\" : \"DESC\"}}\nLIMIT\n  {{Table1.pageSize}}\nOFFSET\n  {{Table1.pageOffset}}",
      "encodeParamsToggle": true,
      "paginationType": "NONE",
      "pluginSpecifiedTemplates": [
        {
          "value": false
        }
      ],
      "timeoutInMillisecond": 10000
    },
    "confirmBeforeExecute": false,
    "datasource": {
      "id": "dify (1)",
      "isAutoGenerated": false,
      "name": "dify (1)",
      "pluginId": "postgres-plugin"
    },
    "dynamicBindingPathList": [
      {
        "key": "body"
      }
    ],
    "executeOnLoad": true,
    "name": "AppsQueryByPage",
    "pageId": "应用报表",
    "userSetOnLoad": false
  }
}